rra_tools/__init__.py
rra_tools/cli_tools/__init__.py
rra_tools/cli_tools/exceptions.py
rra_tools/cli_tools/importers.py
rra_tools/cli_tools/options.py
rra_tools/jobmon.py
rra_tools/logging/__init__.py
rra_tools/logging/config.py
rra_tools/logging/performance.py
rra_tools/logging/protocol.py
rra_tools/parallel.py
rra_tools/plotting.py
rra_tools/py.typed
rra_tools/shell_tools.py
rra_tools/translate.py
rra_tools-1.0.27.dist-info/LICENSE
rra_tools-1.0.27.dist-info/METADATA
rra_tools-1.0.27.dist-info/WHEEL
rra_tools-1.0.27.dist-info/entry_points.txt
rra_tools-1.0.27.dist-info/RECORD
