Metadata-Version: 2.3
Name: rra-tools
Version: 1.0.27
Summary: Common utilities for IHME Rapid Response team pipelines.
License: BSD-3-Clause
Author: James Collins
Author-email: collijk@uw.edu
Requires-Python: >=3.12
Classifier: License :: OSI Approved :: BSD License
Classifier: Programming Language :: Python :: 3
Classifier: Programming Language :: Python :: 3.12
Classifier: Programming Language :: Python :: 3.13
Requires-Dist: click (>=8.0)
Requires-Dist: deep-translator (>=1.11)
Requires-Dist: loguru (>=0.7.0)
Requires-Dist: matplotlib
Requires-Dist: pandas (>=2.2)
Requires-Dist: pathos (>=0.3.3)
Requires-Dist: requests (>=2.0)
Requires-Dist: seaborn
Requires-Dist: tqdm (>=4.0)
Project-URL: Documentation, https://ihmeuw.github.io/rra-tools
Project-URL: Homepage, https://ihmeuw.github.io/rra-tools
Project-URL: Repository, https://ihmeuw.github.io/rra-tools
